LICENSE
nameko_vault/__init__.py
nameko_vault-0.4.0.dist-info/LICENSE
nameko_vault-0.4.0.dist-info/METADATA
nameko_vault-0.4.0.dist-info/WHEEL
nameko_vault-0.4.0.dist-info/RECORD
