Metadata-Version: 2.1
Name: nameko-vault
Version: 0.4.0
Summary: A Nameko extension to provide connection with Vault
Home-page: https://github.com/instruct-br/nameko-vault
License: MIT
Keywords: nameko,vault
Author: Instruct Developers
Author-email: oss@instruct.com.br
Requires-Python: >=3.6,<4.0
Classifier: License :: OSI Approved :: MIT License
Classifier: Operating System :: OS Independent
Classifier: Programming Language :: Python :: 3
Classifier: Programming Language :: Python :: 3.6
Classifier: Programming Language :: Python :: 3.7
Classifier: Programming Language :: Python :: 3.8
Classifier: Programming Language :: Python :: 3.9
Classifier: Programming Language :: Python :: 3.10
Classifier: Programming Language :: Python :: 3.11
Requires-Dist: hvac (>=0.10.5,<0.11.0)
Requires-Dist: nameko (>=2.12.0,<3.0.0)
Project-URL: Repository, https://github.com/instruct-br/nameko-vault
